{
  "main": {
    "id": "7239a5916ec47b92",
    "type": "split",
    "children": [
      {
        "id": "3a5a9153ed6da1e1",
        "type": "tabs",
        "dimension": 21.00253807106599,
        "children": [
          {
            "id": "c476d954d55fdc47",
            "type": "leaf",
            "state": {
              "type": "outline",
              "state": {
                "file": "包管理器/npm/npm.md"
              }
            }
          }
        ]
      },
      {
        "id": "b4a9b66de3ed3dbb",
        "type": "tabs",
        "dimension": 78.99746192893402,
        "children": [
          {
            "id": "3b420eef33aa4b2b",
            "type": "leaf",
            "state": {
              "type": "markdown",
              "state": {
                "file": "包管理器/npm/npm.md",
                "mode": "source",
                "source": false
              }
            }
          }
        ]
      }
    ],
    "direction": "vertical"
  },
  "left": {
    "id": "8dbf378ef556ab14",
    "type": "split",
    "children": [
      {
        "id": "fca2147610bf6f43",
        "type": "tabs",
        "children": [
          {
            "id": "f1aaa7c11777ecdb",
            "type": "leaf",
            "state": {
              "type": "file-explorer",
              "state": {
                "sortOrder": "alphabetical"
              }
            }
          },
          {
            "id": "2f1d61b75654b5a0",
            "type": "leaf",
            "state": {
              "type": "search",
              "state": {
                "query": "",
                "matchingCase": false,
                "explainSearch": false,
                "collapseAll": false,
                "extraContext": false,
                "sortOrder": "alphabetical"
              }
            }
          },
          {
            "id": "9355be27922e836d",
            "type": "leaf",
            "state": {
              "type": "bookmarks",
              "state": {}
            }
          }
        ]
      }
    ],
    "direction": "horizontal",
    "width": 300
  },
  "right": {
    "id": "2eeda14a82bd41ea",
    "type": "split",
    "children": [
      {
        "id": "a9e704dc872ee78b",
        "type": "tabs",
        "children": [
          {
            "id": "f87a14e7be94a049",
            "type": "leaf",
            "state": {
              "type": "backlink",
              "state": {
                "file": "包管理器/npm/npm.md",
                "collapseAll": false,
                "extraContext": false,
                "sortOrder": "alphabetical",
                "showSearch": false,
                "searchQuery": "",
                "backlinkCollapsed": false,
                "unlinkedCollapsed": true
              }
            }
          },
          {
            "id": "c5fcea6d69b8f860",
            "type": "leaf",
            "state": {
              "type": "outgoing-link",
              "state": {
                "file": "包管理器/npm/npm.md",
                "linksCollapsed": false,
                "unlinkedCollapsed": true
              }
            }
          },
          {
            "id": "eb2deada9973b288",
            "type": "leaf",
            "state": {
              "type": "tag",
              "state": {
                "sortOrder": "frequency",
                "useHierarchy": true
              }
            }
          },
          {
            "id": "3d2752d7e643c3f0",
            "type": "leaf",
            "state": {
              "type": "outline",
              "state": {
                "file": "包管理器/npm/npm.md"
              }
            }
          }
        ]
      }
    ],
    "direction": "horizontal",
    "width": 300,
    "collapsed": true
  },
  "left-ribbon": {
    "hiddenItems": {
      "switcher:打开快速切换": false,
      "graph:查看关系图谱": false,
      "canvas:新建白板": false,
      "daily-notes:打开/创建今天的日记": false,
      "templates:插入模板": false,
      "command-palette:打开命令面板": false
    }
  },
  "active": "f1aaa7c11777ecdb",
  "lastOpenFiles": [
    "包管理器/npx/npx~.md",
    "包管理器/npm/images/publish005.png",
    "包管理器/npm/images/publish004.png",
    "包管理器/npm/images/publish003.png",
    "包管理器/npm/images/publish002.png",
    "包管理器/npm/images/publish001.png",
    "包管理器/npm/images",
    "包管理器/npm/未命名文件夹",
    "2024-03-25.md",
    "未命名.canvas",
    "包管理器/npm/npm.md"
  ]
}